[{"id":"14","discoId":"65","number":"01","title":"Dandelion","titleReal":"\u30c0\u30f3\u30c7\u30e9\u30a4\u30aa\u30f3","live":"1","deleted":"0","created":"2014-05-04 14:22:49","modified":"2014-05-04 14:22:49"}, {"id":"15","discoId":"65","number":"DVD","title":"Dandelion (MV)","titleReal":"\u30c0\u30f3\u30c7\u30e9\u30a4\u30aa\u30f3","live":"1","deleted":"0","created":"2014-05-04 14:24:01","modified":"2014-05-04 14:24:01"}, {"id":"16","discoId":"66","number":"01","title":"Dandelion","titleReal":"\u30c0\u30f3\u30c7\u30e9\u30a4\u30aa\u30f3","live":"1","deleted":"0","created":"2014-05-04 14:32:41","modified":"2014-05-04 14:32:41"}, {"id":"17","discoId":"66","number":"02","title":"Juliet No Knife","titleReal":"\u30b8\u30e5\u30ea\u30a8\u30c3\u30c8\u306e\u30ca\u30a4\u30d5","live":"1","deleted":"0","created":"2014-05-04 14:33:08","modified":"2014-05-04 14:33:08"}, {"id":"18","discoId":"66","number":"03","title":"Tsumina Batsu","titleReal":"\u7f6a\u306a\u7f70","live":"1","deleted":"0","created":"2014-05-04 14:33:36","modified":"2014-05-04 14:33:36"}, {"id":"19","discoId":"66","number":"04","title":"Seaside Avenue","titleReal":"","live":"1","deleted":"0","created":"2014-05-04 14:33:50","modified":"2014-05-04 14:33:50"}, {"id":"20","discoId":"66","number":"05","title":"Sunday Driver","titleReal":"","live":"1","deleted":"0","created":"2014-05-04 14:34:03","modified":"2014-05-04 14:34:03"}, {"id":"21","discoId":"66","number":"06","title":"PSYCHEDELIC HEAVEN","titleReal":"","live":"1","deleted":"0","created":"2014-05-04 14:34:16","modified":"2014-05-04 14:34:16"}, {"id":"22","discoId":"66","number":"07","title":"Shikisai Vivid","titleReal":"\u8272\u5f69\u30f4\u30a3\u30f4\u30a3\u30c3\u30c9","live":"1","deleted":"0","created":"2014-05-04 14:34:38","modified":"2014-05-04 14:34:38"}, {"id":"23","discoId":"66","number":"08","title":"Hoshizora To Kimi no Te","titleReal":"\u661f\u7a7a\u3068\u541b\u306e\u624b","live":"1","deleted":"0","created":"2014-05-04 14:35:08","modified":"2014-05-04 14:35:08"}, {"id":"24","discoId":"66","number":"09","title":"Drum Solo","titleReal":"","live":"1","deleted":"0","created":"2014-05-04 14:35:22","modified":"2014-05-04 14:35:22"}, {"id":"25","discoId":"66","number":"10","title":"SMILE WORLD","titleReal":"","live":"1","deleted":"0","created":"2014-05-04 14:35:34","modified":"2014-05-04 14:35:34"}, {"id":"26","discoId":"66","number":"11","title":"aquarium","titleReal":"","live":"1","deleted":"0","created":"2014-05-04 14:35:45","modified":"2014-05-04 14:35:45"}, {"id":"27","discoId":"66","number":"12","title":"Endless Song","titleReal":"","live":"1","deleted":"0","created":"2014-05-04 14:35:57","modified":"2014-05-04 14:35:57"}, {"id":"28","discoId":"66","number":"13","title":"Setsubo No Freesia","titleReal":"\u5207\u671b\u306e\u30d5\u30ea\u30fc\u30b8\u30a2","live":"1","deleted":"0","created":"2014-05-04 14:36:28","modified":"2014-05-04 14:36:28"}, {"id":"29","discoId":"66","number":"14","title":"BIRTHDAY SONG","titleReal":"","live":"1","deleted":"0","created":"2014-05-04 14:36:44","modified":"2014-05-04 14:36:44"}, {"id":"30","discoId":"66","number":"15","title":"SHINE","titleReal":"","live":"1","deleted":"0","created":"2014-05-04 14:36:56","modified":"2014-05-04 14:36:56"}, {"id":"31","discoId":"66","number":"16","title":"BLACK DROPPer","titleReal":"","live":"1","deleted":"0","created":"2014-05-04 14:37:09","modified":"2014-05-04 14:37:09"}, {"id":"32","discoId":"66","number":"17","title":"Little Ballerina","titleReal":"","live":"1","deleted":"0","created":"2014-05-04 14:37:22","modified":"2014-05-04 14:37:22"}, {"id":"33","discoId":"66","number":"18","title":"Bremen","titleReal":"","live":"1","deleted":"0","created":"2014-05-04 14:37:33","modified":"2014-05-04 14:37:33"}, {"id":"34","discoId":"66","number":"19","title":"Tresor","titleReal":"\u30c8\u30ec\u30be\u30a2","live":"1","deleted":"0","created":"2014-05-04 14:37:54","modified":"2014-05-04 14:37:54"}, {"id":"35","discoId":"66","number":"20","title":"Kanojo Wa Emerald","titleReal":"\u5f7c\u5973\u306f\u30a8\u30e1\u30e9\u30eb\u30c9","live":"1","deleted":"0","created":"2014-05-04 14:38:20","modified":"2014-05-04 14:38:20"}, {"id":"36","discoId":"66","number":"21","title":"decade","titleReal":"","live":"1","deleted":"0","created":"2014-05-04 14:38:33","modified":"2014-05-04 14:38:33"}, {"id":"37","discoId":"66","number":"22","title":"KISS YOU","titleReal":"","live":"1","deleted":"0","created":"2014-05-04 14:38:45","modified":"2014-05-04 14:38:45"}, {"id":"38","discoId":"66","number":"23","title":"STAY GOLD","titleReal":"","live":"1","deleted":"0","created":"2014-05-04 14:38:54","modified":"2014-05-04 14:38:54"}, {"id":"39","discoId":"67","number":"SE","title":"KAMAKURA","titleReal":"","live":"1","deleted":"0","created":"2014-05-04 14:42:48","modified":"2014-05-04 14:42:48"}, {"id":"40","discoId":"67","number":"01","title":"Adam","titleReal":"","live":"1","deleted":"0","created":"2014-05-04 14:42:58","modified":"2014-05-04 14:42:58"}, {"id":"41","discoId":"67","number":"02","title":"Tanshoku No Yume","titleReal":"\u6de1\u8272\u306e\u5922","live":"1","deleted":"0","created":"2014-05-04 14:43:20","modified":"2014-05-04 14:43:20"}, {"id":"42","discoId":"67","number":"03","title":"DIRTY SATRRY","titleReal":"","live":"1","deleted":"0","created":"2014-05-04 14:43:33","modified":"2014-05-04 14:43:33"}, {"id":"43","discoId":"67","number":"04","title":"Seaside Avenue","titleReal":"","live":"1","deleted":"0","created":"2014-05-04 14:43:46","modified":"2014-05-04 14:43:46"}, {"id":"44","discoId":"67","number":"05","title":"last note","titleReal":"","live":"1","deleted":"0","created":"2014-05-04 14:43:59","modified":"2014-05-04 14:43:59"}, {"id":"45","discoId":"67","number":"06","title":"Knock Shadow","titleReal":"","live":"1","deleted":"0","created":"2014-05-04 14:44:12","modified":"2014-05-04 14:44:12"}, {"id":"46","discoId":"67","number":"07","title":"Zetsubo no Asa","titleReal":"\u7d76\u671b\u306e\u671d","live":"1","deleted":"0","created":"2014-05-04 14:44:37","modified":"2014-05-04 14:44:37"}, {"id":"47","discoId":"67","number":"08","title":"Twilight (Piano Solo)","titleReal":"","live":"1","deleted":"0","created":"2014-05-04 14:44:56","modified":"2014-05-04 14:44:56"}, {"id":"48","discoId":"67","number":"09","title":"Drum Solo","titleReal":"","live":"1","deleted":"0","created":"2014-05-04 14:45:10","modified":"2014-05-04 14:45:10"}, {"id":"49","discoId":"67","number":"10","title":"Sunday Driver","titleReal":"","live":"1","deleted":"0","created":"2014-05-04 14:45:20","modified":"2014-05-04 14:45:20"}, {"id":"50","discoId":"67","number":"11","title":"Yasokyoku","titleReal":"\u591c\u60f3\u66f2","live":"1","deleted":"0","created":"2014-05-04 14:45:40","modified":"2014-05-04 14:45:40"}, {"id":"51","discoId":"67","number":"12","title":"Akenosora ni Saku","titleReal":"\u831c\u7a7a\u306b\u54b2\u304f","live":"1","deleted":"0","created":"2014-05-04 14:46:11","modified":"2014-05-04 14:46:11"}, {"id":"52","discoId":"67","number":"13","title":"BIRTHDAY SONG","titleReal":"","live":"1","deleted":"0","created":"2014-05-04 14:46:23","modified":"2014-05-04 14:46:23"}, {"id":"53","discoId":"67","number":"14","title":"Dandelion","titleReal":"\u30c0\u30f3\u30c7\u30e9\u30a4\u30aa\u30f3","live":"1","deleted":"0","created":"2014-05-04 14:46:44","modified":"2014-05-04 14:46:44"}, {"id":"54","discoId":"67","number":"15","title":"Diamond Glitter","titleReal":"","live":"1","deleted":"0","created":"2014-05-04 14:47:00","modified":"2014-05-04 14:47:00"}, {"id":"55","discoId":"67","number":"16","title":"BLACK DROPPer","titleReal":"","live":"1","deleted":"0","created":"2014-05-04 14:47:13","modified":"2014-05-04 14:47:13"}, {"id":"56","discoId":"67","number":"17","title":"Another Sky","titleReal":"","live":"1","deleted":"0","created":"2014-05-04 14:47:24","modified":"2014-05-04 14:47:24"}, {"id":"57","discoId":"67","number":"18","title":"KISS YOU","titleReal":"","live":"1","deleted":"0","created":"2014-05-04 14:47:33","modified":"2014-05-04 14:47:33"}, {"id":"58","discoId":"67","number":"19","title":"Tsumina Batsu","titleReal":"\u7f6a\u306a\u7f70","live":"1","deleted":"0","created":"2014-05-04 14:47:53","modified":"2014-05-04 14:47:53"}, {"id":"59","discoId":"67","number":"20","title":"Tsuki ni Jyusei","titleReal":"\u6708\u306b\u9283\u58f0","live":"1","deleted":"0","created":"2014-05-04 14:48:15","modified":"2014-05-04 14:48:15"}, {"id":"60","discoId":"67","number":"21","title":"Purple Candy","titleReal":"","live":"1","deleted":"0","created":"2014-05-04 14:48:28","modified":"2014-05-04 14:48:28"}, {"id":"61","discoId":"67","number":"22","title":"decade","titleReal":"","live":"1","deleted":"0","created":"2014-05-04 14:48:41","modified":"2014-05-04 14:48:41"}, {"id":"62","discoId":"67","number":"23","title":"STAY GOLD","titleReal":"","live":"1","deleted":"0","created":"2014-05-04 14:48:52","modified":"2014-05-04 14:48:52"}, {"id":"63","discoId":"82","number":"01","title":"Make it Through","titleReal":"","live":"1","deleted":"0","created":"2014-05-08 23:58:02","modified":"2014-05-08 23:58:02"}, {"id":"64","discoId":"83","number":"01","title":"The World is Yours","titleReal":"","live":"1","deleted":"0","created":"2014-05-09 00:01:40","modified":"2014-05-09 00:01:40"}, {"id":"65","discoId":"83","number":"02","title":"Everybody Rock\u2019N Roll","titleReal":"","live":"1","deleted":"0","created":"2014-05-09 00:01:45","modified":"2014-05-09 00:01:45"}, {"id":"66","discoId":"83","number":"03","title":"Naked to my soul","titleReal":"","live":"1","deleted":"0","created":"2014-05-09 00:01:56","modified":"2014-05-09 00:01:56"}, {"id":"67","discoId":"83","number":"04","title":"Hey God","titleReal":"","live":"1","deleted":"0","created":"2014-05-09 00:02:05","modified":"2014-05-09 00:02:05"}, {"id":"68","discoId":"83","number":"05","title":"Don\u2019t ever leave me out","titleReal":"","live":"1","deleted":"0","created":"2014-05-09 00:02:18","modified":"2014-05-09 00:02:18"}, {"id":"69","discoId":"84","number":"01","title":"SLICK","titleReal":"","live":"1","deleted":"0","created":"2014-05-09 00:05:13","modified":"2014-05-09 00:05:13"}, {"id":"70","discoId":"84","number":"02","title":"CLUB ROCK SHIT","titleReal":"","live":"1","deleted":"0","created":"2014-05-09 00:05:22","modified":"2014-05-09 00:05:22"}, {"id":"71","discoId":"84","number":"03","title":"JIVE","titleReal":"","live":"1","deleted":"0","created":"2014-05-09 00:05:33","modified":"2014-05-09 00:05:33"}, {"id":"72","discoId":"84","number":"04","title":"YELLOW CHERRY","titleReal":"","live":"1","deleted":"0","created":"2014-05-09 00:05:43","modified":"2014-05-09 00:05:43"}, {"id":"73","discoId":"84","number":"05","title":"PYTHON","titleReal":"","live":"1","deleted":"0","created":"2014-05-09 00:05:56","modified":"2014-05-09 00:05:56"}, {"id":"74","discoId":"84","number":"06","title":"LEFT OF ME","titleReal":"","live":"1","deleted":"0","created":"2014-05-09 00:06:06","modified":"2014-05-09 00:06:06"}, {"id":"75","discoId":"84","number":"07","title":"OBLIVION HEART","titleReal":"","live":"1","deleted":"0","created":"2014-05-09 00:06:17","modified":"2014-05-09 00:06:17"}, {"id":"76","discoId":"84","number":"08","title":"FIGHT NIGHT","titleReal":"","live":"1","deleted":"0","created":"2014-05-09 00:06:27","modified":"2014-05-09 00:06:27"}, {"id":"77","discoId":"84","number":"09","title":"ALIVE","titleReal":"","live":"1","deleted":"0","created":"2014-05-09 00:06:36","modified":"2014-05-09 00:06:36"}, {"id":"78","discoId":"85","number":"01","title":"ALIVE Acoustic Version","titleReal":"","live":"1","deleted":"0","created":"2014-05-09 00:09:45","modified":"2014-05-09 00:09:45"}, {"id":"79","discoId":"86","number":"01","title":"Don't ever leave me out (Piano Remix)","titleReal":"","live":"1","deleted":"0","created":"2014-05-09 00:12:33","modified":"2014-05-09 00:12:33"}, {"id":"80","discoId":"87","number":"01","title":"FROM YESTERDAY","titleReal":"","live":"1","deleted":"0","created":"2014-05-09 00:15:10","modified":"2014-05-09 00:15:10"}, {"id":"81","discoId":"88","number":"01","title":"EVERYBODY ROCK N'ROLL","titleReal":"","live":"1","deleted":"0","created":"2014-05-09 00:24:36","modified":"2014-05-09 00:24:36"}, {"id":"82","discoId":"88","number":"02","title":"CLUB ROCK SHIT","titleReal":"","live":"1","deleted":"0","created":"2014-05-09 00:24:47","modified":"2014-05-09 00:24:47"}, {"id":"83","discoId":"88","number":"03","title":"YELLOW CHERRY","titleReal":"","live":"1","deleted":"0","created":"2014-05-09 00:25:01","modified":"2014-05-09 00:25:01"}, {"id":"84","discoId":"88","number":"04","title":"OBLIVION HEART","titleReal":"","live":"1","deleted":"0","created":"2014-05-09 00:25:13","modified":"2014-05-09 00:25:13"}, {"id":"85","discoId":"88","number":"05","title":"JIVE","titleReal":"","live":"1","deleted":"0","created":"2014-05-09 00:25:25","modified":"2014-05-09 00:25:25"}, {"id":"86","discoId":"88","number":"06","title":"LEFT OF ME","titleReal":"","live":"1","deleted":"0","created":"2014-05-09 00:25:36","modified":"2014-05-09 00:25:36"}, {"id":"87","discoId":"88","number":"07","title":"SLICK","titleReal":"","live":"1","deleted":"0","created":"2014-05-09 00:25:46","modified":"2014-05-09 00:25:46"}, {"id":"88","discoId":"88","number":"08","title":"NAKED TO MY SOUL","titleReal":"","live":"1","deleted":"0","created":"2014-05-09 00:25:55","modified":"2014-05-09 00:25:55"}, {"id":"89","discoId":"88","number":"09","title":"FIGHT NIGHT","titleReal":"","live":"1","deleted":"0","created":"2014-05-09 00:26:05","modified":"2014-05-09 00:26:05"}, {"id":"90","discoId":"88","number":"10","title":"MAKE IT THROUGH","titleReal":"","live":"1","deleted":"0","created":"2014-05-09 00:26:15","modified":"2014-05-09 00:26:15"}, {"id":"91","discoId":"88","number":"11","title":"ALIVE(Acoustic ver.)","titleReal":"","live":"1","deleted":"0","created":"2014-05-09 00:26:27","modified":"2014-05-09 00:26:27"}, {"id":"92","discoId":"88","number":"12","title":"DON'T EVER LEAVE ME OUT(Piano ver.)","titleReal":"","live":"1","deleted":"0","created":"2014-05-09 00:26:42","modified":"2014-05-09 00:26:42"}, {"id":"93","discoId":"89","number":"01","title":"TheHangedMan","titleReal":"","live":"1","deleted":"0","created":"2014-05-23 22:54:36","modified":"2014-05-23 22:54:36"}, {"id":"94","discoId":"89","number":"02","title":"U&I","titleReal":"","live":"1","deleted":"0","created":"2014-05-23 22:54:44","modified":"2014-05-23 22:54:44"}, {"id":"95","discoId":"89","number":"03","title":"OOO","titleReal":"","live":"1","deleted":"0","created":"2014-05-23 22:54:50","modified":"2014-05-23 22:54:50"}, {"id":"96","discoId":"89","number":"04","title":"Irony","titleReal":"","live":"1","deleted":"0","created":"2014-05-23 22:54:57","modified":"2014-05-23 22:54:57"}, {"id":"97","discoId":"89","number":"05","title":"Karuto","titleReal":"\u30ab\u30eb\u30c8","live":"1","deleted":"0","created":"2014-05-23 22:55:49","modified":"2014-05-23 22:55:49"}, {"id":"98","discoId":"89","number":"06","title":"F.U.B.A.R","titleReal":"","live":"1","deleted":"0","created":"2014-05-23 22:56:45","modified":"2014-05-23 22:56:45"}, {"id":"99","discoId":"89","number":"07","title":"Mani To Hati","titleReal":"\u30de\u30fc\u30cb\u3068\u30cf\u30c6\u30a3","live":"1","deleted":"0","created":"2014-05-23 23:00:40","modified":"2014-05-23 23:00:40"}, {"id":"100","discoId":"89","number":"08","title":"F*** Darlin'","titleReal":"","live":"1","deleted":"0","created":"2014-05-23 23:00:52","modified":"2014-05-23 23:00:52"}, {"id":"101","discoId":"89","number":"09","title":"PsyWar","titleReal":"","live":"1","deleted":"0","created":"2014-05-23 23:01:00","modified":"2014-05-23 23:01:00"}, {"id":"102","discoId":"89","number":"10","title":"Hypernova Remnant","titleReal":"","live":"1","deleted":"0","created":"2014-05-23 23:01:10","modified":"2014-05-23 23:01:10"}, {"id":"103","discoId":"89","number":"11","title":"The End","titleReal":"","live":"1","deleted":"0","created":"2014-05-23 23:01:18","modified":"2014-05-23 23:01:18"}, {"id":"104","discoId":"90","number":"01","title":"Minority\u30fbParade","titleReal":"\u30de\u30a4\u30ce\u30ea\u30c6\u30a3\u30fb\u30d1\u30ec\u30fc\u30c9","live":"1","deleted":"0","created":"2014-05-23 23:13:29","modified":"2014-05-23 23:13:29"}, {"id":"105","discoId":"90","number":"02","title":"Liberty\u30fbBell","titleReal":"\u30ea\u30d0\u30c6\u30a3\u30fb\u30d9\u30eb","live":"1","deleted":"0","created":"2014-05-23 23:13:51","modified":"2014-05-23 23:13:51"}, {"id":"106","discoId":"90","number":"03","title":"Starbust","titleReal":"\u30b9\u30bf\u30fc\u30d0\u30fc\u30b9\u30c8","live":"1","deleted":"0","created":"2014-05-23 23:14:06","modified":"2014-05-23 23:14:06"}, {"id":"107","discoId":"90","number":"04","title":"ZERO-IN","titleReal":"","live":"1","deleted":"0","created":"2014-05-23 23:14:15","modified":"2014-05-23 23:14:15"}, {"id":"108","discoId":"90","number":"05","title":"Galileo","titleReal":"\u30ac\u30ea\u30ec\u30aa","live":"1","deleted":"0","created":"2014-05-23 23:14:30","modified":"2014-05-23 23:14:30"}, {"id":"109","discoId":"90","number":"06","title":"Tenohira","titleReal":"\u638c","live":"1","deleted":"0","created":"2014-05-23 23:14:49","modified":"2014-05-23 23:14:49"}, {"id":"110","discoId":"90","number":"07","title":"Sora hana","titleReal":"\u7a7a\u83ef","live":"1","deleted":"0","created":"2014-05-23 23:15:05","modified":"2014-05-23 23:15:05"}, {"id":"111","discoId":"90","number":"08","title":"Nano\u30fbUniverse","titleReal":"\u30ca\u30ce\u30fb\u30e6\u30cb\u30d0\u30fc\u30b9","live":"1","deleted":"0","created":"2014-05-23 23:15:26","modified":"2014-05-23 23:15:26"}, {"id":"112","discoId":"90","number":"09","title":"Kaze no Misaki","titleReal":"\u98a8\u306e\u5cac","live":"1","deleted":"0","created":"2014-05-23 23:15:48","modified":"2014-05-23 23:15:48"}, {"id":"113","discoId":"90","number":"10","title":"Shinsekai","titleReal":"\u65b0\u4e16\u754c","live":"1","deleted":"0","created":"2014-05-23 23:16:01","modified":"2014-05-23 23:16:01"}, {"id":"114","discoId":"91","number":"01","title":"Justice","titleReal":"","live":"1","deleted":"0","created":"2014-05-24 18:21:33","modified":"2014-05-24 18:21:33"}, {"id":"115","discoId":"91","number":"02","title":"Shelter","titleReal":"\u30b7\u30a7\u30eb\u30bf\u30fc","live":"1","deleted":"0","created":"2014-05-24 18:21:51","modified":"2014-05-24 18:21:51"}, {"id":"116","discoId":"91","number":"03","title":"Memento","titleReal":"","live":"1","deleted":"0","created":"2014-05-24 18:22:13","modified":"2014-05-24 18:22:13"}, {"id":"117","discoId":"91","number":"04","title":"Chijou no Eden","titleReal":"\u5730\u4e0a\u306e\u30a8\u30c7\u30f3","live":"1","deleted":"0","created":"2014-05-24 18:22:29","modified":"2014-05-24 18:22:29"}, {"id":"118","discoId":"91","number":"05","title":"\u221e Cosmology","titleReal":"\u221e\u30b3\u30b9\u30e2\u30ed\u30b8\u30fc","live":"1","deleted":"0","created":"2014-05-24 18:22:53","modified":"2014-05-24 18:22:53"}, {"id":"119","discoId":"91","number":"06","title":"Queen Anne's Revenge","titleReal":"","live":"1","deleted":"0","created":"2014-05-24 18:23:10","modified":"2014-05-24 18:23:10"}, {"id":"120","discoId":"91","number":"07","title":"Koi Uta","titleReal":"\u3053\u3044\u3046\u305f","live":"1","deleted":"0","created":"2014-05-24 18:23:23","modified":"2014-05-24 18:23:23"}, {"id":"121","discoId":"91","number":"08","title":"Dandou Transistor","titleReal":"\u5f3e\u9053\u30c8\u30e9\u30f3\u30b8\u30b9\u30bf","live":"1","deleted":"0","created":"2014-05-24 18:23:41","modified":"2014-05-24 18:23:41"}, {"id":"122","discoId":"91","number":"09","title":"Time Capsule","titleReal":"\u30bf\u30a4\u30e0\u30ab\u30d7\u30bb\u30eb","live":"1","deleted":"0","created":"2014-05-24 18:23:55","modified":"2014-05-24 18:23:55"}, {"id":"123","discoId":"91","number":"10","title":"Mizukagami","titleReal":"\u6c34\u93e1","live":"1","deleted":"0","created":"2014-05-24 18:24:09","modified":"2014-05-24 18:24:09"}, {"id":"124","discoId":"91","number":"11","title":"M\u00f6nster","titleReal":"","live":"1","deleted":"0","created":"2014-05-24 18:24:15","modified":"2014-05-24 18:24:15"}, {"id":"125","discoId":"92","number":"01","title":"Omega Rythm","titleReal":"\u30aa\u30e1\u30ac\u30ea\u30ba\u30e0","live":"1","deleted":"0","created":"2014-05-24 18:33:30","modified":"2014-05-24 18:33:30"}, {"id":"126","discoId":"92","number":"02","title":"Nanatsu No Uni","titleReal":"\u4e03\u3064\u306e\u6d77","live":"1","deleted":"0","created":"2014-05-24 18:33:48","modified":"2014-05-24 18:33:48"}, {"id":"127","discoId":"92","number":"03","title":"Ami Da Kuji","titleReal":"\u3042\u307f\u3060\u304f\u3058","live":"1","deleted":"0","created":"2014-05-24 18:34:13","modified":"2014-05-24 18:34:13"}, {"id":"128","discoId":"92","number":"04","title":"Klein no Shinzou","titleReal":"\u30af\u30e9\u30a4\u30f3\u306e\u5fc3\u81d3","live":"1","deleted":"0","created":"2014-05-24 18:34:29","modified":"2014-05-24 18:34:29"}, {"id":"129","discoId":"92","number":"05","title":"Ginga Sekidou","titleReal":"\u9280\u6cb3\u8d64\u9053","live":"1","deleted":"0","created":"2014-05-24 18:34:48","modified":"2014-05-24 18:34:48"}, {"id":"130","discoId":"92","number":"06","title":"Peace","titleReal":"","live":"1","deleted":"0","created":"2014-05-24 18:34:56","modified":"2014-05-24 18:34:56"}, {"id":"131","discoId":"92","number":"07","title":"dot sight","titleReal":"","live":"1","deleted":"0","created":"2014-05-24 18:35:03","modified":"2014-05-24 18:35:03"}, {"id":"132","discoId":"92","number":"08","title":"Boku Wa Dummy","titleReal":"\u50d5\u306f\u30c0\u30df\u30fc","live":"1","deleted":"0","created":"2014-05-24 18:35:17","modified":"2014-05-24 18:35:17"}, {"id":"133","discoId":"92","number":"09","title":"Present","titleReal":"\u30d7\u30ec\u30bc\u30f3\u30c8","live":"1","deleted":"0","created":"2014-05-24 18:35:31","modified":"2014-05-24 18:35:31"}, {"id":"134","discoId":"92","number":"10","title":"diiorama","titleReal":"","live":"1","deleted":"0","created":"2014-05-24 18:35:42","modified":"2014-05-24 18:35:42"}, {"id":"135","discoId":"93","number":"01","title":"Oni","titleReal":"\u9b3c","live":"1","deleted":"0","created":"2014-05-24 18:46:17","modified":"2014-05-24 18:46:17"}, {"id":"136","discoId":"93","number":"02","title":"Kanojo","titleReal":"\u30ab\u30ce\u30b8\u30e7","live":"1","deleted":"0","created":"2014-05-24 18:46:27","modified":"2014-05-24 18:46:27"}, {"id":"137","discoId":"93","number":"03","title":"hallelujah","titleReal":"","live":"1","deleted":"0","created":"2014-05-24 18:46:35","modified":"2014-05-24 18:46:35"}, {"id":"138","discoId":"93","number":"04","title":"=","titleReal":"","live":"1","deleted":"0","created":"2014-05-24 18:46:39","modified":"2014-05-24 18:46:39"}, {"id":"139","discoId":"93","number":"05","title":"NGC224","titleReal":"","live":"1","deleted":"0","created":"2014-05-24 18:46:47","modified":"2014-05-24 18:46:47"}, {"id":"140","discoId":"93","number":"06","title":"Pandora no Hako","titleReal":"\u30d1\u30f3\u30c9\u30e9\u306e\u7bb1","live":"1","deleted":"0","created":"2014-05-24 18:47:02","modified":"2014-05-24 18:47:02"}, {"id":"141","discoId":"93","number":"07","title":"Muguet","titleReal":"\u30df\u30e5\u30b2\u30fc","live":"1","deleted":"0","created":"2014-05-24 18:47:15","modified":"2014-05-24 18:47:15"}, {"id":"142","discoId":"93","number":"08","title":"Mikansei","titleReal":"\u672a\u5b8c\u6210","live":"1","deleted":"0","created":"2014-05-24 18:47:28","modified":"2014-05-24 18:47:28"}, {"id":"143","discoId":"93","number":"09","title":"Matenrou","titleReal":"\u6469\u5929\u697c","live":"1","deleted":"0","created":"2014-05-24 18:47:43","modified":"2014-05-24 18:47:43"}, {"id":"144","discoId":"93","number":"10","title":"Hana to Chou","titleReal":"\u83ef\u3068\u8776","live":"1","deleted":"0","created":"2014-05-24 18:47:58","modified":"2014-05-24 18:47:58"}, {"id":"145","discoId":"93","number":"11","title":"Bodyguard","titleReal":"\u30dc\u30c7\u30a3\u30fc\u30ac\u30fc\u30c9","live":"1","deleted":"0","created":"2014-05-24 18:48:12","modified":"2014-05-24 18:48:12"}, {"id":"146","discoId":"93","number":"12","title":"Katachi","titleReal":"\u30ab\u30bf\u30c1","live":"1","deleted":"0","created":"2014-05-24 18:48:29","modified":"2014-05-24 18:48:29"}, {"id":"147","discoId":"94","number":"01","title":"Nijuusan Ya","titleReal":"\u4e8c\u5341\u4e09\u591c","live":"1","deleted":"0","created":"2014-05-24 18:54:09","modified":"2014-05-24 18:54:09"}, {"id":"148","discoId":"94","number":"02","title":"Syndrome","titleReal":"\u30b7\u30f3\u30c9\u30ed\u30fc\u30e0","live":"1","deleted":"0","created":"2014-05-24 18:54:33","modified":"2014-05-24 18:54:33"}, {"id":"149","discoId":"94","number":"03","title":"ten no kawa","titleReal":"\u5929\u306e\u5ddd","live":"1","deleted":"0","created":"2014-05-24 18:54:49","modified":"2014-05-24 18:54:49"}, {"id":"150","discoId":"94","number":"04","title":"raiu","titleReal":"\u96f7\u96e8","live":"1","deleted":"0","created":"2014-05-24 18:55:00","modified":"2014-05-24 18:55:00"}, {"id":"151","discoId":"94","number":"05","title":"komaku","titleReal":"\u9f13\u819c","live":"1","deleted":"0","created":"2014-05-24 18:55:14","modified":"2014-05-24 18:55:14"}, {"id":"152","discoId":"94","number":"06","title":"Skate Board","titleReal":"\u30b9\u30b1\u30fc\u30c8\u30dc\u30fc\u30c9","live":"1","deleted":"0","created":"2014-05-24 18:55:26","modified":"2014-05-24 18:55:26"}, {"id":"153","discoId":"95","number":"01","title":"Hanabi no Iro","titleReal":"\u82b1\u706b\u306e\u8272","live":"1","deleted":"0","created":"2014-05-24 19:05:12","modified":"2014-05-24 19:05:12"}, {"id":"154","discoId":"95","number":"02","title":"Kikyuu ni Natta Fuusen","titleReal":"\u6c17\u7403\u306b\u306a\u3063\u305f\u98a8\u8239","live":"1","deleted":"0","created":"2014-05-24 19:05:30","modified":"2014-05-24 19:05:30"}, {"id":"155","discoId":"95","number":"03","title":"Shiroi Hato","titleReal":"\u767d\u3044\u9ce9","live":"1","deleted":"0","created":"2014-05-24 19:05:47","modified":"2014-05-24 19:05:47"}, {"id":"156","discoId":"95","number":"03","title":"Shiroi Hato","titleReal":"\u767d\u3044\u9ce9","live":"1","deleted":"0","created":"2014-05-24 19:05:48","modified":"2014-05-24 19:05:48"}, {"id":"157","discoId":"95","number":"04","title":"Niji no Fumoto","titleReal":"\u8679\u306e\u3075\u3082\u3068","live":"1","deleted":"0","created":"2014-05-24 19:06:16","modified":"2014-05-24 19:06:16"}, {"id":"158","discoId":"95","number":"05","title":"Mahou no Komori Uta","titleReal":"\u9b54\u6cd5\u306e\u5b50\u5b88\u5504","live":"1","deleted":"0","created":"2014-05-24 19:06:42","modified":"2014-05-24 19:06:42"}, {"id":"159","discoId":"96","number":"01","title":"Shateki","titleReal":"\u5c04\u7684","live":"1","deleted":"0","created":"2014-05-24 19:17:23","modified":"2014-05-24 19:17:23"}, {"id":"160","discoId":"96","number":"02","title":"Amazarashi","titleReal":"\u96e8\u3056\u3089\u3057","live":"1","deleted":"0","created":"2014-05-24 19:17:46","modified":"2014-05-24 19:17:46"}, {"id":"161","discoId":"96","number":"03","title":"M31","titleReal":"","live":"1","deleted":"0","created":"2014-05-24 19:17:54","modified":"2014-05-24 19:17:54"}, {"id":"162","discoId":"96","number":"04","title":"Enogu","titleReal":"\u7d75\u306e\u5177","live":"1","deleted":"0","created":"2014-05-24 19:18:11","modified":"2014-05-24 19:18:11"}, {"id":"163","discoId":"96","number":"05","title":"Aozora ga nijin da hi","titleReal":"\u9752\u7a7a\u304c\u6ef2\u3093\u3060\u65e5","live":"1","deleted":"0","created":"2014-05-24 19:18:28","modified":"2014-05-24 19:18:28"}, {"id":"164","discoId":"115","number":"01","title":"Vive Le Roi","titleReal":"","live":"1","deleted":"0","created":"2014-08-21 12:09:18","modified":"2014-08-21 12:09:18"}, {"id":"165","discoId":"115","number":"02","title":"Rose Croix","titleReal":"","live":"1","deleted":"0","created":"2014-08-21 12:09:26","modified":"2014-08-21 12:09:26"}, {"id":"166","discoId":"115","number":"03","title":"Yamiyo No Lion","titleReal":"\u95c7\u591c\u306e\u30e9\u30a4\u30aa\u30f3","live":"1","deleted":"0","created":"2014-08-21 12:09:46","modified":"2014-08-21 12:09:46"}, {"id":"167","discoId":"115","number":"04","title":"Louis ~Enketsu no la Vie En Rose~","titleReal":"Louis \uff5e\u8276\u8840\u306e\u30e9\u30f4\u30a3\u30a2\u30f3\u30ed\u30fc\u30ba\uff5e","live":"1","deleted":"0","created":"2014-08-21 12:10:10","modified":"2014-08-21 12:10:10"}, {"id":"168","discoId":"115","number":"05","title":"Death Parade","titleReal":"","live":"1","deleted":"0","created":"2014-08-21 12:10:20","modified":"2014-08-21 12:10:20"}, {"id":"169","discoId":"115","number":"06","title":"Romantique","titleReal":"","live":"1","deleted":"0","created":"2014-08-21 12:10:27","modified":"2014-08-21 12:10:27"}, {"id":"170","discoId":"115","number":"07","title":"Dakishime Rarenagara","titleReal":"\u62b1\u304d\u3057\u3081\u3089\u308c\u306a\u304c\u3089","live":"1","deleted":"0","created":"2014-08-21 12:10:50","modified":"2014-08-21 12:10:50"}, {"id":"171","discoId":"115","number":"08","title":"Moulin Rouge","titleReal":"","live":"1","deleted":"0","created":"2014-08-21 12:11:00","modified":"2014-08-21 12:11:00"}, {"id":"172","discoId":"115","number":"09","title":"Sanctuary","titleReal":"\u30b5\u30f3\u30af\u30c1\u30e5\u30a2\u30ea","live":"1","deleted":"0","created":"2014-08-21 12:11:31","modified":"2014-08-21 12:11:31"}, {"id":"173","discoId":"115","number":"10","title":"Katate ni yume o motsu sh\u00f6jo","titleReal":"\u7247\u624b\u306b\u5922\u3092\u6301\u3064\u5c11\u5973","live":"1","deleted":"0","created":"2014-08-21 12:11:55","modified":"2014-08-21 12:11:55"}, {"id":"174","discoId":"115","number":"11","title":"Tsuioku no Mon Amour","titleReal":"\u8ffd\u61b6\u306e\u30e2\u30ca\u30e0\u30fc\u30eb","live":"1","deleted":"0","created":"2014-08-21 12:12:16","modified":"2014-08-21 12:12:16"}, {"id":"175","discoId":"115","number":"12","title":"Heart","titleReal":"","live":"1","deleted":"0","created":"2014-08-21 12:12:23","modified":"2014-08-21 12:12:23"}, {"id":"176","discoId":"116","number":"01","title":"Vive Le Roi","titleReal":"","live":"1","deleted":"0","created":"2014-08-21 12:18:26","modified":"2014-08-21 12:18:26"}, {"id":"177","discoId":"116","number":"02","title":"Rose Croix","titleReal":"","live":"1","deleted":"0","created":"2014-08-21 12:18:34","modified":"2014-08-21 12:18:34"}, {"id":"178","discoId":"116","number":"03","title":"Yamiyo No Lion","titleReal":"","live":"1","deleted":"0","created":"2014-08-21 12:18:42","modified":"2014-08-21 12:18:42"}, {"id":"179","discoId":"116","number":"04","title":"Louis ~Enketsu No La Vie En Rose~","titleReal":"","live":"1","deleted":"0","created":"2014-08-21 12:18:56","modified":"2014-08-21 12:18:56"}, {"id":"180","discoId":"116","number":"05","title":"Death Parade","titleReal":"","live":"1","deleted":"0","created":"2014-08-21 12:19:03","modified":"2014-08-21 12:19:03"}, {"id":"181","discoId":"116","number":"06","title":"Romantique","titleReal":"","live":"1","deleted":"0","created":"2014-08-21 12:19:09","modified":"2014-08-21 12:19:09"}, {"id":"182","discoId":"116","number":"07","title":"Dakishime Rarenagara","titleReal":"","live":"1","deleted":"0","created":"2014-08-21 12:19:20","modified":"2014-08-21 12:19:20"}, {"id":"183","discoId":"116","number":"08","title":"Moulin Rouge","titleReal":"","live":"1","deleted":"0","created":"2014-08-21 12:19:28","modified":"2014-08-21 12:19:28"}, {"id":"184","discoId":"116","number":"09","title":"Sanctuary","titleReal":"","live":"1","deleted":"0","created":"2014-08-21 12:19:36","modified":"2014-08-21 12:19:36"}, {"id":"185","discoId":"116","number":"10","title":"Katate ni yume o motsu sh\u00f6jo","titleReal":"","live":"1","deleted":"0","created":"2014-08-21 12:19:48","modified":"2014-08-21 12:19:48"}, {"id":"186","discoId":"116","number":"11","title":"Tsuioku no Mon Amour","titleReal":"","live":"1","deleted":"0","created":"2014-08-21 12:19:57","modified":"2014-08-21 12:19:57"}, {"id":"187","discoId":"116","number":"12","title":"Heart","titleReal":"","live":"1","deleted":"0","created":"2014-08-21 12:20:01","modified":"2014-08-21 12:20:01"}]